btproxipy/__init__.py
btproxipy/bt_rssi.py
btproxipy/btproxipy.py
home/luke/.config/btproxipy/btproxipy.ini
home/luke/.local/share/systemd/user/btproxipy.service
btproxipy-0.2.dist-info/METADATA
btproxipy-0.2.dist-info/WHEEL
btproxipy-0.2.dist-info/entry_points.txt
btproxipy-0.2.dist-info/top_level.txt
btproxipy-0.2.dist-info/RECORD
